oauth2/__init__.py
oauth2/_version.py
oauth2-1.9rc1.dist-info/DESCRIPTION.rst
oauth2-1.9rc1.dist-info/METADATA
oauth2-1.9rc1.dist-info/metadata.json
oauth2-1.9rc1.dist-info/RECORD
oauth2-1.9rc1.dist-info/top_level.txt
oauth2-1.9rc1.dist-info/WHEEL
oauth2-1.9rc1.dist-info/zip-safe
